pygame_input.py
pygame_input-0.1.1.dist-info/LICENSE
pygame_input-0.1.1.dist-info/WHEEL
pygame_input-0.1.1.dist-info/METADATA
pygame_input-0.1.1.dist-info/RECORD
