Metadata-Version: 2.1
Name: pygame-input
Version: 0.1.1
Summary: pygame-input is a tool to simplify input handling with pygame
Home-page: https://gitlab.com/ddorn/pygame-input
License: MIT
Keywords: pygame,input,game,joystick
Author: Diego Dorn
Author-email: pygame-input@lama-corp.space
Requires-Python: >=3.6,<4.0
Classifier: License :: OSI Approved :: MIT License
Classifier: Programming Language :: Python :: 3
Classifier: Programming Language :: Python :: 3.6
Classifier: Programming Language :: Python :: 3.7
Classifier: Programming Language :: Python :: 3.8
Requires-Dist: pygame (>=1.9.0,<2.0.0)
Project-URL: Repository, https://gitlab.com/ddorn/pygame-input
